MANIFEST.in
README.md
VERSION
setup.py
../../LICENSE
simple_health_checks/additional_configs/rabbitmq_config.py
simple_health_checks/resources/rabbitmq.py
simple_health_checks_rabbitmq.egg-info/PKG-INFO
simple_health_checks_rabbitmq.egg-info/SOURCES.txt
simple_health_checks_rabbitmq.egg-info/dependency_links.txt
simple_health_checks_rabbitmq.egg-info/requires.txt
simple_health_checks_rabbitmq.egg-info/top_level.txt