Metadata-Version: 2.1
Name: simple-health-checks-rabbitmq
Version: 1.0.1
Summary: RabbitMQ plugin for simple-health-checks
Home-page: https://gitlab.com/genomicsengland/opensource/simple-healthchecks
Author: Nicholas Dentandt, Oleg Gerasimenko, Constantina Polycarpou
Author-email: noreply@genomicsengland.co.uk
License: Apache License 2.0
Platform: UNKNOWN
Provides-Extra: tests
Provides-Extra: dev
